timer_event/__init__.py
timer_event/event_thread.py
timer_event/timer_event.py
timer_event-0.9.1.dist-info/LICENSE.txt
timer_event-0.9.1.dist-info/METADATA
timer_event-0.9.1.dist-info/WHEEL
timer_event-0.9.1.dist-info/top_level.txt
timer_event-0.9.1.dist-info/RECORD
