Metadata-Version: 2.1
Name: timer-event
Version: 0.9.1
Summary: The package offers thread-safe classes for event-driven programming, including a versatile Event class for managing callback routines and a TimerEvent class for creating repeated timer-based events.
Download-URL: https://github.com/erolyesin/timer_event/archive/refs/tags/v0.9.1-rc02.tar.gz
Author-email: Erol Yesin <erol@sandboxzilla.net>
Project-URL: Homepage, https://github.com/erolyesin/timer_event
Project-URL: Bug Tracker, https://https://github.com/erolyesin/timer_event/issues
Keywords: event,thread-safe,event-driven,timer-based events,repeated events,callback
Classifier: Development Status :: 4 - Beta
Classifier: Intended Audience :: Developers
Classifier: Topic :: Software Development :: Build Tools
Classifier: License :: OSI Approved :: MIT License
Classifier: Programming Language :: Python :: 3.6
Classifier: Programming Language :: Python :: 3.8
Classifier: Programming Language :: Python :: 3.9
Classifier: Programming Language :: Python :: 3.10
Classifier: Operating System :: OS Independent
Requires-Python: >=3.6
License-File: LICENSE.txt
